setup.py
ecs_mon/__init__.py
ecs_mon/__main__.py
ecs_mon/ecs_mon.py
ecs_mon/version.py
ecs_mon.egg-info/PKG-INFO
ecs_mon.egg-info/SOURCES.txt
ecs_mon.egg-info/dependency_links.txt
ecs_mon.egg-info/entry_points.txt
ecs_mon.egg-info/requires.txt
ecs_mon.egg-info/top_level.txt