Metadata-Version: 1.1
Name: ecs-mon
Version: 0.0.4
Summary: A CLI to easily monitor AWS ECS Service
Home-page: https://github.com/modernix/ecs-mon
Author: Ben Tran
Author-email: ben.btran@gmail.com
License: MIT
Keywords: aws-ecs,ecs service,monitor
Platform: UNKNOWN
Classifier: Intended Audience :: Developers
Classifier: Natural Language :: English
Classifier: License :: OSI Approved :: MIT License
Classifier: Programming Language :: Python
Classifier: Programming Language :: Python :: 2
Classifier: Programming Language :: Python :: 2.7
Classifier: Programming Language :: Python :: 3
Classifier: Programming Language :: Python :: 3.6
